Metadata-Version: 1.0
Name: my-awesome-package-amway
Version: 0.1.2
Summary: My awesome package
Home-page: https://gitlab.com/pypri/pypri-gitlab-ci
Author: Me
Author-email: uni2k11@gmail.com
License: MIT
Platform: UNKNOWN
